hypercube/__init__.py
hypercube/client.py
hypercube_client-0.0.1.dist-info/LICENSE
hypercube_client-0.0.1.dist-info/LICENSE~
hypercube_client-0.0.1.dist-info/METADATA
hypercube_client-0.0.1.dist-info/WHEEL
hypercube_client-0.0.1.dist-info/top_level.txt
hypercube_client-0.0.1.dist-info/RECORD
